{
  "hypothesis_id": "cross_school_fdi_hightech_developmental_1990_2023",
  "verdict_label": "PARTIAL",
  "verdict_reason": "coefficient is not statistically decisive at p <= 0.10",
  "n_observations": 2494,
  "n_countries": 180,
  "formula": "Q('high_tech_exports') ~ Q('fdi') + Q('gdp_pc_growth') + C(country) + C(year)",
  "coefficient": 0.0007621475929351732,
  "standard_error_cluster_country": 0.003382202969502757,
  "p_value": 0.8217143298319736,
  "ci95": [
    -0.005866848415694653,
    0.007391143601565
  ],
  "direction": "+",
  "treatment": "fdi",
  "outcome": "high_tech_exports",
  "controls": [
    "gdp_pc_growth"
  ],
  "run_utc": "2026-05-12T19:20:03+00:00",
  "runner": "scripts/promote_cross_school_next50_2026_05_12.py",
  "school_focus": [
    "developmentalism",
    "empirical_pragmatist"
  ],
  "batch": "04_developmental_institutional"
}