{
  "verdict": "BLOCKED \u2014 required city/metro-level outcomes not in vintages (5 missing). Hypothesis is pre-registered ahead of fetcher work; running on country-level proxy would conflate treatment dilution with absence of effect. See BLOCKED.md.",
  "blocked": true,
  "all_pass": false,
  "missing_data": [
    "bls:CUURS12B_rent_nyc_msa",
    "bls:CUURS24B_rent_minneapolis_msa",
    "bls:CUURS35B_rent_portland_msa",
    "eurostat:prc_hpi_q_berlin",
    "us_census:BPS_permits_metro"
  ],
  "found_data": [],
  "cohorts_pre_registered": [
    {
      "unit": "berlin_de",
      "treat": "2020-02-23",
      "country": "DEU",
      "policy": "Mietendeckel"
    },
    {
      "unit": "stpaul_us",
      "treat": "2021-11-02",
      "country": "USA",
      "policy": "St Paul rent stabilisation"
    },
    {
      "unit": "nyc_us",
      "treat": "2019-06-14",
      "country": "USA",
      "policy": "HSTPA"
    },
    {
      "unit": "oregon_us",
      "treat": "2019-02-28",
      "country": "USA",
      "policy": "SB-608"
    }
  ],
  "estimator_template": "did_callaway_santanna",
  "next_steps": [
    "Ship BLS MSA-level rent CPI fetcher (CUURS12B/S24B/S35B)",
    "Ship US Census BPS metro permit fetcher",
    "Ship Eurostat subnational HPI / Berlin Statistik fetcher",
    "Re-run; replication.py auto-detects vintages and proceeds"
  ]
}
