[
  {
    "position_id": "social_democratic",
    "position_file": "positions/social_democratic.yaml",
    "claim_index": 0,
    "claim_text": "Nordic outcomes require BOTH welfare architecture AND institutional quality \u2014 welfare is not secondary.",
    "claim_school_prediction": "mixed",
    "claim_polarity": "aligned",
    "claim_scope": {
      "period": [
        1996,
        2023
      ],
      "countries": [
        "NOR",
        "SWE",
        "DNK",
        "FIN",
        "ISL",
        "NORDIC"
      ],
      "outcome_dim": [
        "welfare_state",
        "institutional_quality",
        "poverty_inequality"
      ],
      "policy_family": [
        "welfare_architecture",
        "institutional_reform"
      ],
      "treatment_tags": [
        "nordic_welfare_model",
        "universal_welfare_architecture"
      ]
    },
    "claim_notes": "Social democrats push back on the framework's claim that welfare is downstream of institutions.",
    "linked_hypothesis_id": "nordic_outcome_persistence_decomposition",
    "hypothesis_file": "hypotheses/institutional_quality/nordic_outcome_persistence_decomposition.yaml",
    "hypothesis_topic": "institutional_quality",
    "hypothesis_claim": "Nordic persistent outcome advantages (GDP per capita, Gini disposable income, unemployment) over comparable high-welfare Southern European economies over 1996-2023 are substantially explained by a decomposable set of institutional, market-economy, and fiscal-discipline features \u2014 specifically government effectiveness, rule of law, and debt-to-GDP ratio \u2014 rather than by welfare architecture or Nordic-specific cultural factors alone. Country-specific residuals after channel controls and country fixed effects should account for a minority of the raw Nordic-vs-Southern-Europe outcome gap.\n",
    "hypothesis_scope": {
      "period": [
        1996,
        2023
      ],
      "countries": [
        "NOR",
        "SWE",
        "DNK",
        "FIN",
        "ISL",
        "ESP",
        "ITA",
        "GRC",
        "PRT",
        "FRA",
        "NORDIC",
        "SOUTHERN_EUROPE"
      ],
      "outcome_dim": [
        "institutional_quality",
        "gdp_growth",
        "welfare_state",
        "poverty_inequality"
      ],
      "policy_family": [
        "institutional_reform",
        "welfare_architecture",
        "fiscal_policy"
      ],
      "treatment_tags": [
        "nordic_model",
        "nordic_welfare_architecture",
        "government_effectiveness_channel",
        "rule_of_law_channel",
        "debt_to_gdp_channel"
      ]
    },
    "hypothesis_sample_countries": [
      "NOR",
      "SWE",
      "DNK",
      "FIN",
      "ISL",
      "ESP",
      "ITA",
      "GRC",
      "PRT",
      "FRA"
    ],
    "hypothesis_sample_period": [
      1996,
      2023
    ],
    "covers_claims_entry": {
      "position_id": "social_democratic",
      "claim_index": 0,
      "polarity": "aligned",
      "school_prediction": "mixed",
      "confidence": "medium",
      "notes": "Social-democratic claim that welfare is co-necessary with institutions is the direct counter-framing the hypothesis adjudicates via channel decomposition."
    },
    "error_axes": [
      "treatment_tags"
    ],
    "error_messages": [
      "treatment_tags: claim treatment_tags ['nordic_welfare_model', 'universal_welfare_architecture'] disjoint from hypothesis treatment_tags ['debt_to_gdp_channel', 'government_effectiveness_channel', 'nordic_model', 'nordic_welfare_architecture', 'rule_of_law_channel']"
    ],
    "suggested_action_class": "WIDEN_OR_RELINK"
  },
  {
    "position_id": "social_democratic",
    "position_file": "positions/social_democratic.yaml",
    "claim_index": 7,
    "claim_text": "US-EU GDP-per-capita gap is partly driven by hours-worked differences that reflect welfare-state preferences (more leisure, more public services) rather than productivity deficit.",
    "claim_school_prediction": "supported",
    "claim_polarity": "inverted",
    "claim_scope": {
      "period": [
        1970,
        2023
      ],
      "countries": [
        "USA",
        "EU",
        "EUROZONE"
      ],
      "outcome_dim": [
        "gdp_growth",
        "productivity",
        "employment_labour"
      ],
      "policy_family": [
        "labour_market",
        "welfare_architecture"
      ],
      "treatment_tags": [
        "hours_worked_preference",
        "european_leisure_preference"
      ]
    },
    "claim_notes": null,
    "linked_hypothesis_id": "us_eu_gdp_per_capita_divergence_policy_causes",
    "hypothesis_file": "hypotheses/growth/us_eu_gdp_per_capita_divergence_policy_causes.yaml",
    "hypothesis_topic": "growth",
    "hypothesis_claim": "US GDP per capita (PPP, constant $) exceeds the EU15 weighted average by approximately 50% as of 2023, with the gap widening from ~20% in 2000 after converging during 1980-1995. The divergence is primarily explained by policy-channel differences that are empirically separable from demographic, geographic, or capital-stock differences: (a) US product- market deregulation and competition-policy activism vs EU regulatory density (OECD PMR); (b) US labour-market flexibility vs EU employment protection (OECD EPL); (c) capital-market depth and venture-financing breadth; (d) energy-cost differential post-2011 driven by shale vs Energiewende/gas-import dependence; (e) tax structure favouring capital formation. The claim is that demographic + trade-openness + human-capital controls leave policy channels as the binding explanation.\n",
    "hypothesis_scope": {
      "period": [
        1970,
        2023
      ],
      "countries": [
        "USA",
        "DEU",
        "FRA",
        "ITA",
        "ESP",
        "NLD",
        "BEL",
        "AUT",
        "FIN",
        "DNK",
        "SWE",
        "IRL",
        "PRT",
        "GRC",
        "LUX",
        "EU",
        "EUROZONE"
      ],
      "outcome_dim": [
        "gdp_growth",
        "productivity",
        "institutional_quality"
      ],
      "policy_family": [
        "regulation",
        "labour_market",
        "tax_policy",
        "institutional_reform"
      ],
      "treatment_tags": [
        "us_eu_policy_divergence",
        "pmr_epl_divergence"
      ]
    },
    "hypothesis_sample_countries": [
      "USA",
      "DEU",
      "FRA",
      "ITA",
      "ESP",
      "NLD",
      "BEL",
      "AUT",
      "FIN",
      "DNK",
      "SWE",
      "IRL",
      "PRT",
      "GRC",
      "LUX"
    ],
    "hypothesis_sample_period": [
      1970,
      2023
    ],
    "covers_claims_entry": {
      "position_id": "social_democratic",
      "claim_index": 7,
      "polarity": "inverted",
      "school_prediction": "supported",
      "confidence": "medium",
      "notes": "Inverted-polarity overlap: social democratic claim attributes US-EU GDP gap to hours-worked/leisure-preference rather than productivity deficit \u2014 directly contrary to this hypothesis's policy-channel explanation, sharing same sample/scope."
    },
    "error_axes": [
      "treatment_tags"
    ],
    "error_messages": [
      "treatment_tags: claim treatment_tags ['european_leisure_preference', 'hours_worked_preference'] disjoint from hypothesis treatment_tags ['pmr_epl_divergence', 'us_eu_policy_divergence']"
    ],
    "suggested_action_class": "WIDEN_OR_RELINK"
  }
]
