{
  "hypothesis_id": "eurostat_electricity_price_volatility_industrial_exit",
  "verdict_label": "PARTIAL",
  "verdict_reason": "coefficient is not statistically decisive at p<0.10",
  "n_observations": 192,
  "n_countries": 33,
  "period_min": 2019,
  "period_max": 2024,
  "formula": "Q('industry_employment_share') ~ Q('electricity_price_volatility') + Q('gdp_pc_growth') + C(country) + C(year)",
  "coefficient": 0.0054811455306699695,
  "standard_error_cluster_country": 0.004536005836298124,
  "p_value": 0.22690733383028083,
  "ci95": [
    -0.0034092625421378413,
    0.01437155360347778
  ],
  "direction": "-",
  "treatment": "electricity_price_volatility",
  "outcome": "industry_employment_share",
  "controls": [
    "gdp_pc_growth"
  ],
  "run_utc": "2026-05-12T19:55:25+00:00",
  "runner": "scripts/promote_eurostat_energy_batch06_2026_05_12.py",
  "school_focus": [
    "austrian",
    "ordoliberal",
    "developmentalism"
  ],
  "batch": "06_eurostat_energy_prices_nuclear_transition"
}
