{
  "series": [
    {
      "year": 1961,
      "high_credit_gap": 0,
      "mean_outcome": 3.0810912088618925
    },
    {
      "year": 1962,
      "high_credit_gap": 0,
      "mean_outcome": 2.6058269091991364
    },
    {
      "year": 1963,
      "high_credit_gap": 0,
      "mean_outcome": 2.456271066989827
    },
    {
      "year": 1964,
      "high_credit_gap": 0,
      "mean_outcome": 2.166532523802354
    },
    {
      "year": 1965,
      "high_credit_gap": 0,
      "mean_outcome": 2.329482862690047
    },
    {
      "year": 1966,
      "high_credit_gap": 0,
      "mean_outcome": 2.1526059505810338
    },
    {
      "year": 1967,
      "high_credit_gap": 0,
      "mean_outcome": 1.9906660491030996
    },
    {
      "year": 1968,
      "high_credit_gap": 0,
      "mean_outcome": 2.1769269972095384
    },
    {
      "year": 1969,
      "high_credit_gap": 0,
      "mean_outcome": 1.464060983993683
    },
    {
      "year": 1970,
      "high_credit_gap": 0,
      "mean_outcome": 1.5239905893974066
    },
    {
      "year": 1971,
      "high_credit_gap": 0,
      "mean_outcome": 2.2948925008632965
    },
    {
      "year": 1972,
      "high_credit_gap": 0,
      "mean_outcome": 2.0201675319532075
    },
    {
      "year": 1973,
      "high_credit_gap": 0,
      "mean_outcome": 1.8454510111014795
    },
    {
      "year": 1973,
      "high_credit_gap": 1,
      "mean_outcome": 0.38596346669758835
    },
    {
      "year": 1974,
      "high_credit_gap": 0,
      "mean_outcome": 2.0857173455920828
    },
    {
      "year": 1974,
      "high_credit_gap": 1,
      "mean_outcome": 1.3401052210697921
    },
    {
      "year": 1975,
      "high_credit_gap": 0,
      "mean_outcome": 2.5194248171534435
    },
    {
      "year": 1976,
      "high_credit_gap": 0,
      "mean_outcome": 2.227459204066208
    },
    {
      "year": 1977,
      "high_credit_gap": 0,
      "mean_outcome": 1.7914267447440029
    },
    {
      "year": 1977,
      "high_credit_gap": 1,
      "mean_outcome": 2.567463748259871
    },
    {
      "year": 1978,
      "high_credit_gap": 0,
      "mean_outcome": 1.7642460159168316
    },
    {
      "year": 1978,
      "high_credit_gap": 1,
      "mean_outcome": 0.9174900603541118
    },
    {
      "year": 1979,
      "high_credit_gap": 0,
      "mean_outcome": 1.878893303442959
    },
    {
      "year": 1979,
      "high_credit_gap": 1,
      "mean_outcome": 0.8203845262024535
    },
    {
      "year": 1980,
      "high_credit_gap": 0,
      "mean_outcome": 2.0747861834294823
    },
    {
      "year": 1980,
      "high_credit_gap": 1,
      "mean_outcome": 0.851269017697525
    },
    {
      "year": 1981,
      "high_credit_gap": 0,
      "mean_outcome": 2.2296021784034568
    },
    {
      "year": 1981,
      "high_credit_gap": 1,
      "mean_outcome": 1.3752729271416733
    },
    {
      "year": 1982,
      "high_credit_gap": 0,
      "mean_outcome": 2.5832051183257048
    },
    {
      "year": 1982,
      "high_credit_gap": 1,
      "mean_outcome": 1.6059266874966056
    },
    {
      "year": 1983,
      "high_credit_gap": 0,
      "mean_outcome": 2.694806525757087
    },
    {
      "year": 1983,
      "high_credit_gap": 1,
      "mean_outcome": 6.51379255791745
    },
    {
      "year": 1984,
      "high_credit_gap": 0,
      "mean_outcome": 3.009045550825394
    },
    {
      "year": 1984,
      "high_credit_gap": 1,
      "mean_outcome": 2.9462073651644225
    },
    {
      "year": 1985,
      "high_credit_gap": 0,
      "mean_outcome": 2.9404352820881394
    },
    {
      "year": 1985,
      "high_credit_gap": 1,
      "mean_outcome": 3.5179850757631925
    },
    {
      "year": 1986,
      "high_credit_gap": 0,
      "mean_outcome": 2.877903815338318
    },
    {
      "year": 1986,
      "high_credit_gap": 1,
      "mean_outcome": 1.2579678979607416
    },
    {
      "year": 1987,
      "high_credit_gap": 0,
      "mean_outcome": 2.6182205723033913
    },
    {
      "year": 1987,
      "high_credit_gap": 1,
      "mean_outcome": 1.2058015315192776
    },
    {
      "year": 1988,
      "high_credit_gap": 0,
      "mean_outcome": 1.9286768341246696
    },
    {
      "year": 1988,
      "high_credit_gap": 1,
      "mean_outcome": 0.8268527892380777
    },
    {
      "year": 1989,
      "high_credit_gap": 0,
      "mean_outcome": 2.096040277928366
    },
    {
      "year": 1989,
      "high_credit_gap": 1,
      "mean_outcome": 0.9346663863802924
    },
    {
      "year": 1990,
      "high_credit_gap": 0,
      "mean_outcome": 2.1163619497841264
    },
    {
      "year": 1990,
      "high_credit_gap": 1,
      "mean_outcome": 1.3617645654350317
    },
    {
      "year": 1991,
      "high_credit_gap": 0,
      "mean_outcome": 2.487321632404148
    },
    {
      "year": 1991,
      "high_credit_gap": 1,
      "mean_outcome": 1.7430445491296171
    },
    {
      "year": 1992,
      "high_credit_gap": 0,
      "mean_outcome": 2.8377265238004563
    },
    {
      "year": 1992,
      "high_credit_gap": 1,
      "mean_outcome": 2.2852040102359488
    },
    {
      "year": 1993,
      "high_credit_gap": 0,
      "mean_outcome": 2.7043608746514125
    },
    {
      "year": 1993,
      "high_credit_gap": 1,
      "mean_outcome": 2.645255182078576
    },
    {
      "year": 1994,
      "high_credit_gap": 0,
      "mean_outcome": 2.825924467939206
    },
    {
      "year": 1994,
      "high_credit_gap": 1,
      "mean_outcome": 1.71610860215462
    },
    {
      "year": 1995,
      "high_credit_gap": 0,
      "mean_outcome": 2.982388054114103
    },
    {
      "year": 1995,
      "high_credit_gap": 1,
      "mean_outcome": 1.2087952953320233
    },
    {
      "year": 1996,
      "high_credit_gap": 0,
      "mean_outcome": 2.8508271106736314
    },
    {
      "year": 1996,
      "high_credit_gap": 1,
      "mean_outcome": 0.9851775383298921
    },
    {
      "year": 1997,
      "high_credit_gap": 0,
      "mean_outcome": 2.59497568098721
    },
    {
      "year": 1997,
      "high_credit_gap": 1,
      "mean_outcome": 1.1555485097906377
    },
    {
      "year": 1998,
      "high_credit_gap": 0,
      "mean_outcome": 2.375435287116294
    },
    {
      "year": 1998,
      "high_credit_gap": 1,
      "mean_outcome": 3.2905766672229246
    },
    {
      "year": 1999,
      "high_credit_gap": 0,
      "mean_outcome": 2.6154766061810966
    },
    {
      "year": 1999,
      "high_credit_gap": 1,
      "mean_outcome": 2.6673816752630066
    },
    {
      "year": 2000,
      "high_credit_gap": 0,
      "mean_outcome": 2.2930308826416805
    },
    {
      "year": 2000,
      "high_credit_gap": 1,
      "mean_outcome": 2.5553389979039087
    },
    {
      "year": 2001,
      "high_credit_gap": 0,
      "mean_outcome": 2.789646780728502
    },
    {
      "year": 2001,
      "high_credit_gap": 1,
      "mean_outcome": 2.3573905888249627
    },
    {
      "year": 2002,
      "high_credit_gap": 0,
      "mean_outcome": 3.0905558863994664
    },
    {
      "year": 2002,
      "high_credit_gap": 1,
      "mean_outcome": 2.625213923148696
    },
    {
      "year": 2003,
      "high_credit_gap": 0,
      "mean_outcome": 2.687089107195811
    },
    {
      "year": 2003,
      "high_credit_gap": 1,
      "mean_outcome": 2.6208992203179973
    },
    {
      "year": 2004,
      "high_credit_gap": 0,
      "mean_outcome": 1.4912298759565132
    },
    {
      "year": 2004,
      "high_credit_gap": 1,
      "mean_outcome": 0.6053981428615357
    },
    {
      "year": 2005,
      "high_credit_gap": 0,
      "mean_outcome": 1.6597300099338863
    },
    {
      "year": 2005,
      "high_credit_gap": 1,
      "mean_outcome": 0.3019834667880842
    },
    {
      "year": 2006,
      "high_credit_gap": 0,
      "mean_outcome": 1.714676184512717
    },
    {
      "year": 2006,
      "high_credit_gap": 1,
      "mean_outcome": -0.4316261471009896
    },
    {
      "year": 2007,
      "high_credit_gap": 0,
      "mean_outcome": 1.5338823412723217
    },
    {
      "year": 2007,
      "high_credit_gap": 1,
      "mean_outcome": -0.6660420318607719
    },
    {
      "year": 2008,
      "high_credit_gap": 0,
      "mean_outcome": 1.7394990751278194
    },
    {
      "year": 2008,
      "high_credit_gap": 1,
      "mean_outcome": -0.3848641445191211
    },
    {
      "year": 2009,
      "high_credit_gap": 0,
      "mean_outcome": 2.5029650924623654
    },
    {
      "year": 2009,
      "high_credit_gap": 1,
      "mean_outcome": 1.0205782939500199
    },
    {
      "year": 2010,
      "high_credit_gap": 0,
      "mean_outcome": 1.769153216334946
    },
    {
      "year": 2010,
      "high_credit_gap": 1,
      "mean_outcome": 1.461959658646403
    },
    {
      "year": 2011,
      "high_credit_gap": 0,
      "mean_outcome": 1.5156168411560809
    },
    {
      "year": 2011,
      "high_credit_gap": 1,
      "mean_outcome": 1.8051890500401615
    },
    {
      "year": 2012,
      "high_credit_gap": 0,
      "mean_outcome": 1.7649860903716375
    },
    {
      "year": 2012,
      "high_credit_gap": 1,
      "mean_outcome": 2.380225825335453
    },
    {
      "year": 2013,
      "high_credit_gap": 0,
      "mean_outcome": 1.8411688364416197
    },
    {
      "year": 2013,
      "high_credit_gap": 1,
      "mean_outcome": 3.124430223161467
    },
    {
      "year": 2014,
      "high_credit_gap": 0,
      "mean_outcome": 1.8153575146439322
    },
    {
      "year": 2014,
      "high_credit_gap": 1,
      "mean_outcome": 2.7931084380012012
    },
    {
      "year": 2015,
      "high_credit_gap": 0,
      "mean_outcome": 0.5090280265753844
    },
    {
      "year": 2015,
      "high_credit_gap": 1,
      "mean_outcome": 1.036079856407726
    },
    {
      "year": 2016,
      "high_credit_gap": 0,
      "mean_outcome": 1.5737933248719893
    },
    {
      "year": 2016,
      "high_credit_gap": 1,
      "mean_outcome": 1.7351820760332126
    },
    {
      "year": 2017,
      "high_credit_gap": 0,
      "mean_outcome": 1.7247052346114946
    },
    {
      "year": 2017,
      "high_credit_gap": 1,
      "mean_outcome": 1.6273624483445683
    },
    {
      "year": 2018,
      "high_credit_gap": 0,
      "mean_outcome": 1.4447373081760309
    },
    {
      "year": 2018,
      "high_credit_gap": 1,
      "mean_outcome": -0.04681216461060005
    },
    {
      "year": 2019,
      "high_credit_gap": 0,
      "mean_outcome": 1.42279700981396
    },
    {
      "year": 2019,
      "high_credit_gap": 1,
      "mean_outcome": 0.09882678519266169
    }
  ]
}