{
  "kind": "result",
  "chart_id": "uk_nationalised_industry_investment_rates/fig1",
  "title": "Gross capital formation share of GDP, 1950-1979",
  "subtitle": "UK mean 23.0% vs DEU+FRA mean 31.9% \u00b7 gap -8.9pp \u00b7 SUPPORTED band \u00b15pp \u00b7 REFUTED if UK below by >10pp.",
  "type": "line",
  "x_axis": {
    "label": "Year",
    "type": "linear"
  },
  "y_axis": {
    "label": "csh_i (gross capital formation / GDP, current PPPs)",
    "type": "linear"
  },
  "series": [
    {
      "id": "GBR",
      "label": "GBR",
      "color": "#E15759",
      "treated": true,
      "points": [
        {
          "x": 1950,
          "y": 0.14997893571853638
        },
        {
          "x": 1951,
          "y": 0.2069411277770996
        },
        {
          "x": 1952,
          "y": 0.1741013377904892
        },
        {
          "x": 1953,
          "y": 0.1857876479625702
        },
        {
          "x": 1954,
          "y": 0.18742720782756805
        },
        {
          "x": 1955,
          "y": 0.20377109944820404
        },
        {
          "x": 1956,
          "y": 0.20807307958602905
        },
        {
          "x": 1957,
          "y": 0.2174193412065506
        },
        {
          "x": 1958,
          "y": 0.21105986833572388
        },
        {
          "x": 1959,
          "y": 0.22669917345046997
        },
        {
          "x": 1960,
          "y": 0.2509285509586334
        },
        {
          "x": 1961,
          "y": 0.24285879731178284
        },
        {
          "x": 1962,
          "y": 0.22422373294830322
        },
        {
          "x": 1963,
          "y": 0.22641265392303467
        },
        {
          "x": 1964,
          "y": 0.2709362208843231
        },
        {
          "x": 1965,
          "y": 0.26532286405563354
        },
        {
          "x": 1966,
          "y": 0.2574377655982971
        },
        {
          "x": 1967,
          "y": 0.26626595854759216
        },
        {
          "x": 1968,
          "y": 0.27403727173805237
        },
        {
          "x": 1969,
          "y": 0.2705704867839813
        },
        {
          "x": 1970,
          "y": 0.2698272168636322
        },
        {
          "x": 1971,
          "y": 0.2555965781211853
        },
        {
          "x": 1972,
          "y": 0.2364273965358734
        },
        {
          "x": 1973,
          "y": 0.2568168044090271
        },
        {
          "x": 1974,
          "y": 0.2458638697862625
        },
        {
          "x": 1975,
          "y": 0.2171688973903656
        },
        {
          "x": 1976,
          "y": 0.2320593297481537
        },
        {
          "x": 1977,
          "y": 0.22783805429935455
        },
        {
          "x": 1978,
          "y": 0.21956197917461395
        },
        {
          "x": 1979,
          "y": 0.21859167516231537
        }
      ]
    },
    {
      "id": "DEU",
      "label": "DEU",
      "color": "#4E79A7",
      "treated": false,
      "points": [
        {
          "x": 1950,
          "y": 0.3534410893917084
        },
        {
          "x": 1951,
          "y": 0.34692251682281494
        },
        {
          "x": 1952,
          "y": 0.3660253584384918
        },
        {
          "x": 1953,
          "y": 0.3442746698856354
        },
        {
          "x": 1954,
          "y": 0.35890868306159973
        },
        {
          "x": 1955,
          "y": 0.40090274810791016
        },
        {
          "x": 1956,
          "y": 0.38735824823379517
        },
        {
          "x": 1957,
          "y": 0.3771950304508209
        },
        {
          "x": 1958,
          "y": 0.36959895491600037
        },
        {
          "x": 1959,
          "y": 0.395221471786499
        },
        {
          "x": 1960,
          "y": 0.4258593022823334
        },
        {
          "x": 1961,
          "y": 0.40335309505462646
        },
        {
          "x": 1962,
          "y": 0.3895305395126343
        },
        {
          "x": 1963,
          "y": 0.37861117720603943
        },
        {
          "x": 1964,
          "y": 0.4008733034133911
        },
        {
          "x": 1965,
          "y": 0.4029467701911926
        },
        {
          "x": 1966,
          "y": 0.38318613171577454
        },
        {
          "x": 1967,
          "y": 0.3391236960887909
        },
        {
          "x": 1968,
          "y": 0.35159656405448914
        },
        {
          "x": 1969,
          "y": 0.36971527338027954
        },
        {
          "x": 1970,
          "y": 0.38980865478515625
        },
        {
          "x": 1971,
          "y": 0.3700576722621918
        },
        {
          "x": 1972,
          "y": 0.35021570324897766
        },
        {
          "x": 1973,
          "y": 0.33354270458221436
        },
        {
          "x": 1974,
          "y": 0.30044686794281006
        },
        {
          "x": 1975,
          "y": 0.279449462890625
        },
        {
          "x": 1976,
          "y": 0.29234734177589417
        },
        {
          "x": 1977,
          "y": 0.28977251052856445
        },
        {
          "x": 1978,
          "y": 0.29558420181274414
        },
        {
          "x": 1979,
          "y": 0.3232353627681732
        }
      ]
    },
    {
      "id": "FRA",
      "label": "FRA",
      "color": "#59A14F",
      "treated": false,
      "points": [
        {
          "x": 1950,
          "y": 0.22987207770347595
        },
        {
          "x": 1951,
          "y": 0.23552262783050537
        },
        {
          "x": 1952,
          "y": 0.23176328837871552
        },
        {
          "x": 1953,
          "y": 0.22124163806438446
        },
        {
          "x": 1954,
          "y": 0.23528873920440674
        },
        {
          "x": 1955,
          "y": 0.23985376954078674
        },
        {
          "x": 1956,
          "y": 0.25509709119796753
        },
        {
          "x": 1957,
          "y": 0.2681470811367035
        },
        {
          "x": 1958,
          "y": 0.2823709547519684
        },
        {
          "x": 1959,
          "y": 0.27257299423217773
        },
        {
          "x": 1960,
          "y": 0.29457250237464905
        },
        {
          "x": 1961,
          "y": 0.2783935070037842
        },
        {
          "x": 1962,
          "y": 0.27693840861320496
        },
        {
          "x": 1963,
          "y": 0.2814493179321289
        },
        {
          "x": 1964,
          "y": 0.29985716938972473
        },
        {
          "x": 1965,
          "y": 0.2929709553718567
        },
        {
          "x": 1966,
          "y": 0.3016706109046936
        },
        {
          "x": 1967,
          "y": 0.2998458743095398
        },
        {
          "x": 1968,
          "y": 0.30167102813720703
        },
        {
          "x": 1969,
          "y": 0.3172907531261444
        },
        {
          "x": 1970,
          "y": 0.3197968006134033
        },
        {
          "x": 1971,
          "y": 0.3085618019104004
        },
        {
          "x": 1972,
          "y": 0.3053275942802429
        },
        {
          "x": 1973,
          "y": 0.308834969997406
        },
        {
          "x": 1974,
          "y": 0.3117171823978424
        },
        {
          "x": 1975,
          "y": 0.26933157444000244
        },
        {
          "x": 1976,
          "y": 0.2832781672477722
        },
        {
          "x": 1977,
          "y": 0.2780902087688446
        },
        {
          "x": 1978,
          "y": 0.27299734950065613
        },
        {
          "x": 1979,
          "y": 0.28418460488319397
        }
      ]
    },
    {
      "id": "PEER_MEAN",
      "label": "DEU+FRA mean",
      "color": "#1f1f1f",
      "treated": false,
      "points": [
        {
          "x": 1950,
          "y": 0.29165658354759216
        },
        {
          "x": 1951,
          "y": 0.29122257232666016
        },
        {
          "x": 1952,
          "y": 0.29889432340860367
        },
        {
          "x": 1953,
          "y": 0.2827581539750099
        },
        {
          "x": 1954,
          "y": 0.29709871113300323
        },
        {
          "x": 1955,
          "y": 0.32037825882434845
        },
        {
          "x": 1956,
          "y": 0.32122766971588135
        },
        {
          "x": 1957,
          "y": 0.3226710557937622
        },
        {
          "x": 1958,
          "y": 0.3259849548339844
        },
        {
          "x": 1959,
          "y": 0.3338972330093384
        },
        {
          "x": 1960,
          "y": 0.3602159023284912
        },
        {
          "x": 1961,
          "y": 0.3408733010292053
        },
        {
          "x": 1962,
          "y": 0.3332344740629196
        },
        {
          "x": 1963,
          "y": 0.33003024756908417
        },
        {
          "x": 1964,
          "y": 0.3503652364015579
        },
        {
          "x": 1965,
          "y": 0.34795886278152466
        },
        {
          "x": 1966,
          "y": 0.34242837131023407
        },
        {
          "x": 1967,
          "y": 0.31948478519916534
        },
        {
          "x": 1968,
          "y": 0.3266337960958481
        },
        {
          "x": 1969,
          "y": 0.343503013253212
        },
        {
          "x": 1970,
          "y": 0.3548027276992798
        },
        {
          "x": 1971,
          "y": 0.3393097370862961
        },
        {
          "x": 1972,
          "y": 0.3277716487646103
        },
        {
          "x": 1973,
          "y": 0.3211888372898102
        },
        {
          "x": 1974,
          "y": 0.30608202517032623
        },
        {
          "x": 1975,
          "y": 0.2743905186653137
        },
        {
          "x": 1976,
          "y": 0.2878127545118332
        },
        {
          "x": 1977,
          "y": 0.28393135964870453
        },
        {
          "x": 1978,
          "y": 0.28429077565670013
        },
        {
          "x": 1979,
          "y": 0.3037099838256836
        }
      ]
    }
  ],
  "annotations": [
    {
      "type": "note",
      "label": "PWT 10.x csh_i. UK below DEU+FRA mean in 30 of 30 years."
    }
  ],
  "sources": [
    {
      "publisher_id": "pwt",
      "series_id": "csh_i",
      "vintage_file": "data/vintages/pwt/csh_i@2026-04-27T090915Z.parquet"
    }
  ],
  "permalink": "/h/uk_nationalised_industry_investment_rates"
}
